{
  "info": {
    "name": "Healthcare API Tests",
    "description": "API tests for the Healthcare application",
    "schema": "https://schema.getpostman.com/json/collection/v2.1.0/collection.json"
  },
  "item": [
    {
      "name": "Health Check",
      "request": {
        "method": "GET",
        "header": [],
        "url": {
          "raw": "{{baseUrl}}/health",
          "host": ["{{baseUrl}}"],
          "path": ["health"]
        }
      },
      "event": [
        {
          "listen": "test",
          "script": {
            "exec": [
              "pm.test('Status code is 200', function () {",
              "    pm.response.to.have.status(200);",
              "});",
              "",
              "pm.test('Response has status field', function () {",
              "    var jsonData = pm.response.json();",
              "    pm.expect(jsonData).to.have.property('status');",
              "});"
            ],
            "type": "text/javascript"
          }
        }
      ]
    },
    {
      "name": "Get All Appointments",
      "request": {
        "method": "GET",
        "header": [],
        "url": {
          "raw": "{{baseUrl}}/api/appointments",
          "host": ["{{baseUrl}}"],
          "path": ["api", "appointments"]
        }
      },
      "event": [
        {
          "listen": "test",
          "script": {
            "exec": [
              "pm.test('Status code is 200', function () {",
              "    pm.response.to.have.status(200);",
              "});",
              "",
              "pm.test('Response is an array', function () {",
              "    var jsonData = pm.response.json();",
              "    pm.expect(jsonData).to.be.an('array');",
              "});"
            ],
            "type": "text/javascript"
          }
        }
      ]
    },
    {
      "name": "Create Appointment",
      "request": {
        "method": "POST",
        "header": [
          {
            "key": "Content-Type",
            "value": "application/json"
          }
        ],
        "body": {
          "mode": "raw",
          "raw": "{\n  \"patientName\": \"Test Patient\",\n  \"doctorName\": \"Dr. Test\",\n  \"appointmentDate\": \"2025-09-07T10:00:00.000Z\",\n  \"description\": \"Test appointment\"\n}"
        },
        "url": {
          "raw": "{{baseUrl}}/api/appointments",
          "host": ["{{baseUrl}}"],
          "path": ["api", "appointments"]
        }
      },
      "event": [
        {
          "listen": "test",
          "script": {
            "exec": [
              "pm.test('Status code is 201', function () {",
              "    pm.response.to.have.status(201);",
              "});",
              "",
              "pm.test('Response has appointment data', function () {",
              "    var jsonData = pm.response.json();",
              "    pm.expect(jsonData).to.have.property('_id');",
              "    pm.expect(jsonData).to.have.property('patientName');",
              "});"
            ],
            "type": "text/javascript"
          }
        }
      ]
    }
  ],
  "variable": [
    {
      "key": "baseUrl",
      "value": "http://localhost:5001",
      "type": "string"
    }
  ]
}
